demo/__init__.py
demo/demo_oauth.py
demo/demo_verify_token.py
snowland_authsdk/__init__.py
snowland_authsdk/common.py
snowland_authsdk/decorator.py
snowland_authsdk/key_store.py
snowland_authsdk/login.py
snowland_authsdk/sign.py
snowland_authsdk/token_helper.py
snowland_authsdk/util.py
snowland_authsdk-0.0.5.dist-info/DESCRIPTION.rst
snowland_authsdk-0.0.5.dist-info/METADATA
snowland_authsdk-0.0.5.dist-info/RECORD
snowland_authsdk-0.0.5.dist-info/WHEEL
snowland_authsdk-0.0.5.dist-info/metadata.json
snowland_authsdk-0.0.5.dist-info/top_level.txt
