Metadata-Version: 2.0
Name: snowland-authsdk
Version: 0.0.5
Summary: snowland-authsdk, oauth 2.0 framework for Snowland.ltd
Home-page: https://gitee.com/snowlandltd/snowland-auth-sdk-python
Author: A.Star
Author-email: astar@snowland.ltd
License: Apache v2.0
Platform: all
Classifier: Development Status :: 4 - Beta
Classifier: Operating System :: OS Independent
Classifier: Intended Audience :: Developers
Classifier: Programming Language :: Python
Classifier: Programming Language :: Python :: Implementation
Classifier: Programming Language :: Python :: 3
Classifier: Programming Language :: Python :: 3.6
Classifier: Programming Language :: Python :: 3.7
Classifier: Topic :: Software Development :: Libraries
Requires-Dist: requests
Requires-Dist: snowland-smx (>=0.3.1)
Requires-Dist: astartool (>=0.0.1)
Requires-Dist: pycryptodome
Requires-Dist: easydict
Requires-Dist: decorator
